formulations/__init__.py
formulations/formulations.py
formulations-1.2.dist-info/METADATA
formulations-1.2.dist-info/WHEEL
formulations-1.2.dist-info/top_level.txt
formulations-1.2.dist-info/RECORD
