Metadata-Version: 2.1
Name: formulations
Version: 1.2
Summary: A basic moduel that contains many formulas.
Author: Programer-Turtle
